phmutest/__init__.py
phmutest/__main__.py
phmutest/cases.py
phmutest/code.py
phmutest/color.py
phmutest/config.py
phmutest/direct.py
phmutest/fcb.py
phmutest/fenced.py
phmutest/fillin.py
phmutest/fixture.py
phmutest/globs.py
phmutest/importer.py
phmutest/main.py
phmutest/printer.py
phmutest/py.typed
phmutest/reader.py
phmutest/select.py
phmutest/session.py
phmutest/skip.py
phmutest/subtest.py
phmutest/summary.py
phmutest/syntax.py
phmutest/systool.py
phmutest/tool.py
phmutest-1.0.1.dist-info/LICENSE
phmutest-1.0.1.dist-info/METADATA
phmutest-1.0.1.dist-info/WHEEL
phmutest-1.0.1.dist-info/entry_points.txt
phmutest-1.0.1.dist-info/top_level.txt
phmutest-1.0.1.dist-info/RECORD
