Metadata-Version: 2.2
Name: phmutest
Version: 1.0.1
Summary: Detect and troubleshoot broken Python examples in Markdown.
Home-page: https://phmutest.readthedocs.io/en/latest/
Author: Mark Taylor
Author-email: mark66547ta2@gmail.com
License: MIT
Project-URL: Bug Reports, https://github.com/tmarktaylor/phmutest/issues
Project-URL: Source, https://github.com/tmarktaylor/phmutest/
Keywords: documentation,markdown,testing
Classifier: Development Status :: 5 - Production/Stable
Classifier: Environment :: Console
Classifier: Intended Audience :: Developers
Classifier: License :: OSI Approved :: MIT License
Classifier: Operating System :: OS Independent
Classifier: Programming Language :: Python :: 3 :: Only
Classifier: Programming Language :: Python :: 3.8
Classifier: Programming Language :: Python :: 3.9
Classifier: Programming Language :: Python :: 3.10
Classifier: Programming Language :: Python :: 3.11
Classifier: Programming Language :: Python :: 3.12
Classifier: Programming Language :: Python :: 3.13
Classifier: Programming Language :: Python :: Implementation :: PyPy
Classifier: Topic :: Software Development :: Documentation
Classifier: Topic :: Software Development :: Libraries :: Python Modules
Classifier: Topic :: Software Development :: Quality Assurance
Classifier: Topic :: Software Development :: Testing
Requires-Python: >=3.8
License-File: LICENSE
Requires-Dist: tomli>=1.0.0; python_version < "3.11"
Provides-Extra: color
Requires-Dist: colorama>=0.4.6; os_name == "nt" and extra == "color"
Requires-Dist: colorama>=0.4.4; os_name != "nt" and extra == "color"
Requires-Dist: pygments; extra == "color"
Provides-Extra: pytest
Requires-Dist: pytest>=6.2.5; extra == "pytest"
Requires-Dist: pytest-subtests; extra == "pytest"
Provides-Extra: traceback
Requires-Dist: stackprinter; extra == "traceback"
Provides-Extra: dev
Requires-Dist: colorama>=0.4.6; os_name == "nt" and extra == "dev"
Requires-Dist: colorama>=0.4.4; os_name != "nt" and extra == "dev"
Requires-Dist: pygments; extra == "dev"
Requires-Dist: pytest>=6.2.5; extra == "dev"
Requires-Dist: pytest-subtests; extra == "dev"
Requires-Dist: stackprinter; extra == "dev"
Requires-Dist: coverage; extra == "dev"
Requires-Dist: flake8; extra == "dev"
Requires-Dist: pep8-naming; extra == "dev"
Requires-Dist: mkdocs; extra == "dev"
Requires-Dist: mypy; extra == "dev"
Requires-Dist: black; extra == "dev"
Requires-Dist: isort; extra == "dev"
